rd_wrapper/__init__.py
rd_wrapper/rd_wrapper.py
rd_wrapper-0.0.8.dist-info/LICENSE
rd_wrapper-0.0.8.dist-info/METADATA
rd_wrapper-0.0.8.dist-info/WHEEL
rd_wrapper-0.0.8.dist-info/top_level.txt
rd_wrapper-0.0.8.dist-info/RECORD
