Metadata-Version: 2.1
Name: rd-wrapper
Version: 0.0.8
Summary: A simple and easy-to-use Python wrapper for Real-Debrid API (https://api.real-debrid.com)
Home-page: https://github.com/Henrique-Coder/rd-wrapper
Author: Henrique-Coder
Author-email: hjyz6rqyb@mozmail.com
License: MIT
Classifier: Development Status :: 4 - Beta
Classifier: Intended Audience :: Developers
Classifier: Topic :: Software Development :: Libraries
Classifier: License :: OSI Approved :: MIT License
Classifier: Programming Language :: Python :: 3.8
Classifier: Programming Language :: Python :: 3.9
Classifier: Programming Language :: Python :: 3.10
Classifier: Programming Language :: Python :: 3.11
Classifier: Programming Language :: Python :: 3.12
Classifier: Programming Language :: Python :: 3 :: Only
Classifier: Programming Language :: Python :: Implementation :: CPython
Classifier: Programming Language :: Python :: Implementation :: PyPy
Requires-Python: >=3.8
License-File: LICENSE
Requires-Dist: beautifulsoup4
Requires-Dist: fake-useragent
Requires-Dist: httpx
